tests/__init__.py
tests/test_main.py
tests/test_script.py
tests/test_utils.py
weechat_script_lint/__init__.py
weechat_script_lint/main.py
weechat_script_lint/script.py
weechat_script_lint/utils.py
weechat_script_lint-0.6.0.dist-info/licenses/LICENSE.txt
weechat_script_lint-0.6.0.dist-info/METADATA
weechat_script_lint-0.6.0.dist-info/WHEEL
weechat_script_lint-0.6.0.dist-info/entry_points.txt
weechat_script_lint-0.6.0.dist-info/top_level.txt
weechat_script_lint-0.6.0.dist-info/RECORD
