Metadata-Version: 2.4
Name: weechat-script-lint
Version: 0.6.0
Summary: Static analysis tool for WeeChat scripts.
Home-page: https://github.com/weechat/weechat-script-lint
Author: Sébastien Helleu
Author-email: flashcode@flashtux.org
License: GPL3
Keywords: static analysis weechat script lint
Classifier: Development Status :: 5 - Production/Stable
Classifier: Environment :: Console
Classifier: Intended Audience :: Developers
Classifier: License :: OSI Approved :: GNU General Public License v3 or later (GPLv3+)
Classifier: Natural Language :: English
Classifier: Operating System :: OS Independent
Classifier: Programming Language :: Python
Classifier: Programming Language :: Python :: 3
Classifier: Topic :: Software Development
Classifier: Topic :: Utilities
License-File: LICENSE.txt
Dynamic: author
Dynamic: author-email
Dynamic: classifier
Dynamic: description
Dynamic: description-content-type
Dynamic: home-page
Dynamic: keywords
Dynamic: license
Dynamic: license-file
Dynamic: summary
